{"nodes": [{"id": "interactive_upgrade_record_replay", "label": "Record-then-Replay Pattern", "file_type": "concept", "source_file": "INTERACTIVE_UPGRADE.md", "source_location": null, "source_url": null, "captured_at": null, "author": null, "contributor": null}, {"id": "interactive_upgrade_generate_frames", "label": "generateFrames.ts", "file_type": "code", "source_file": "INTERACTIVE_UPGRADE.md", "source_location": null, "source_url": null, "captured_at": null, "author": null, "contributor": null}, {"id": "interactive_upgrade_sort_registry", "label": "sortRegistry.ts", "file_type": "code", "source_file": "INTERACTIVE_UPGRADE.md", "source_location": null, "source_url": null, "captured_at": null, "author": null, "contributor": null}, {"id": "interactive_upgrade_sorting_workspace", "label": "SortingWorkspace", "file_type": "code", "source_file": "INTERACTIVE_UPGRADE.md", "source_location": null, "source_url": null, "captured_at": null, "author": null, "contributor": null}, {"id": "interactive_upgrade_sorting_visualizer", "label": "SortingVisualizer", "file_type": "code", "source_file": "INTERACTIVE_UPGRADE.md", "source_location": null, "source_url": null, "captured_at": null, "author": null, "contributor": null}, {"id": "interactive_upgrade_code_viewer", "label": "CodeViewer", "file_type": "code", "source_file": "INTERACTIVE_UPGRADE.md", "source_location": null, "source_url": null, "captured_at": null, "author": null, "contributor": null}], "edges": [{"source": "interactive_upgrade_sorting_workspace", "target": "interactive_upgrade_generate_frames", "relation": "calls", "confidence": "EXTRACTED", "confidence_score": 1.0, "source_file": "INTERACTIVE_UPGRADE.md", "source_location": null, "weight": 1.0}, {"source": "interactive_upgrade_sorting_workspace", "target": "interactive_upgrade_sort_registry", "relation": "references", "confidence": "EXTRACTED", "confidence_score": 1.0, "source_file": "INTERACTIVE_UPGRADE.md", "source_location": null, "weight": 1.0}, {"source": "interactive_upgrade_sorting_workspace", "target": "interactive_upgrade_sorting_visualizer", "relation": "references", "confidence": "EXTRACTED", "confidence_score": 1.0, "source_file": "INTERACTIVE_UPGRADE.md", "source_location": null, "weight": 1.0}, {"source": "interactive_upgrade_sorting_workspace", "target": "interactive_upgrade_code_viewer", "relation": "references", "confidence": "EXTRACTED", "confidence_score": 1.0, "source_file": "INTERACTIVE_UPGRADE.md", "source_location": null, "weight": 1.0}, {"source": "interactive_upgrade_sorting_workspace", "target": "interactive_upgrade_record_replay", "relation": "conceptually_related_to", "confidence": "EXTRACTED", "confidence_score": 1.0, "source_file": "INTERACTIVE_UPGRADE.md", "source_location": null, "weight": 1.0}, {"source": "interactive_upgrade_generate_frames", "target": "interactive_upgrade_record_replay", "relation": "conceptually_related_to", "confidence": "EXTRACTED", "confidence_score": 1.0, "source_file": "INTERACTIVE_UPGRADE.md", "source_location": null, "weight": 1.0}, {"source": "interactive_upgrade_record_replay", "target": "cartesian_analysis_handbook_features", "relation": "conceptually_related_to", "confidence": "INFERRED", "confidence_score": 0.9, "source_file": "INTERACTIVE_UPGRADE.md", "source_location": null, "weight": 1.0}], "hyperedges": [{"id": "record_replay_flow", "label": "Record-then-Replay Architecture Flow", "nodes": ["interactive_upgrade_record_replay", "interactive_upgrade_generate_frames", "interactive_upgrade_sorting_workspace", "interactive_upgrade_sorting_visualizer", "interactive_upgrade_code_viewer"], "relation": "implement", "confidence": "EXTRACTED", "confidence_score": 0.95, "source_file": "INTERACTIVE_UPGRADE.md"}]}